[
  {
    "url": "https://orari.units.it/agendaweb/index.php?view=easycourse&form-type=corso&include=corso&txtcurr=&anno=2025&scuola=DipartimentodiIngegneriaeArchitettura&corso=AR03A&anno2%5B%5D=PDS0-2025%7C1&visualizzazione_orario=cal&date=2025-11-06&periodo_didattico=&_lang=it&list=&week_grid_type=-1&ar_codes_=&ar_select_=&col_cells=0&empty_box=0&only_grid=0&highlighted_date=0&all_events=0&faculty_group=0",
    "dipartimento": "DipartimentodiIngegneriaeArchitettura",
    "codice corso": "AR03A",
    "corso di studi": "ARCHITETTURA (Laurea Magistrale Ciclo Unico 5 anni)",
    "codice anno corso di studio": "PDS0-2025|1",
    "anno corso e curriculum": "1 - Comune con tutti gli altri curriculum di quel corso",
    "giorno inizio settimana": "03/11/2025",
    "orario lezioni": [
      {
        "data": "03-11-2025",
        "aula": "Aula 202 [Edificio Gorizia]",
        "orario": "09:00 - 13:00",
        "docente": "BORTOT ALESSIO"
      },
      {
        "data": "03-11-2025",
        "aula": "Aula 301 [Edificio Gorizia]",
        "orario": "14:00 - 18:00",
        "docente": "STIVAL CARLO ANTONIO"
      },
      {
        "data": "04-11-2025",
        "aula": "Aula 404 [Edificio Gorizia]",
        "orario": "09:00 - 11:00",
        "docente": "NICOLOSO PAOLO"
      },
      {
        "data": "04-11-2025",
        "aula": "Aula 202 [Edificio Gorizia]",
        "orario": "11:00 - 13:00",
        "docente": "GUARAGNA GIANFRANCO"
      },
      {
        "data": "04-11-2025",
        "aula": "Aula 202 [Edificio Gorizia]",
        "orario": "14:00 - 18:00",
        "docente": "GUARAGNA GIANFRANCO"
      },
      {
        "data": "05-11-2025",
        "aula": "Aula 404 [Edificio Gorizia]",
        "orario": "11:00 - 13:00",
        "docente": "NICOLOSO PAOLO"
      },
      {
        "data": "05-11-2025",
        "aula": "Aula 201 [Edificio Gorizia]",
        "orario": "15:00 - 17:00",
        "docente": "O'LOUGHLIN MARTIN"
      },
      {
        "data": "06-11-2025",
        "aula": "Aula 202 [Edificio Gorizia]",
        "orario": "09:00 - 11:00",
        "docente": "O'LOUGHLIN MARTIN"
      },
      {
        "data": "06-11-2025",
        "aula": "Aula 404 [Edificio Gorizia]",
        "orario": "11:00 - 13:00",
        "docente": "NICOLOSO PAOLO"
      },
      {
        "data": "07-11-2025",
        "aula": "Aula 201 [Edificio Gorizia]",
        "orario": "09:00 - 13:00",
        "docente": "MARZARO MATTIA"
      },
      {
        "data": "07-11-2025",
        "aula": "Aula 404 [Edificio Gorizia]",
        "orario": "11:00 - 13:00",
        "docente": "NICOLOSO PAOLO"
      },
      {
        "data": "07-11-2025",
        "aula": "Aula 202 [Edificio Gorizia]",
        "orario": "14:00 - 16:00",
        "docente": "O'LOUGHLIN MARTIN"
      }
    ]
  }
]