[
  {
    "url": "https://orari.units.it/agendaweb/index.php?view=easycourse&form-type=corso&include=corso&txtcurr=&anno=2025&scuola=DipartimentodiIngegneriaeArchitettura&corso=IN23&anno2%5B%5D=IN23%2B3%2B%7C2&visualizzazione_orario=cal&date=2025-11-06&periodo_didattico=&_lang=it&list=&week_grid_type=-1&ar_codes_=&ar_select_=&col_cells=0&empty_box=0&only_grid=0&highlighted_date=0&all_events=0&faculty_group=0",
    "dipartimento": "DipartimentodiIngegneriaeArchitettura",
    "codice corso": "IN23",
    "corso di studi": "COMPUTER ENGINEERING (Laurea Magistrale)",
    "codice anno corso di studio": "IN23+3+|2",
    "anno corso e curriculum": "2 - ROBOTICS AND ARTIFICIAL INTELLIGENCE",
    "giorno inizio settimana": "03/11/2025",
    "orario lezioni": [
      {
        "data": "03-11-2025",
        "orario": "06:30 - 20:00"
      },
      {
        "data": "04-11-2025",
        "aula": "Aula N [Edificio A]",
        "orario": "14:00 - 16:00",
        "docente": "RAIMONDO DAVIDE MARTINO"
      },
      {
        "data": "05-11-2025",
        "aula": "Aula B [Edificio C9]",
        "orario": "09:00 - 12:00",
        "docente": "SALVATO ERICA"
      },
      {
        "data": "05-11-2025",
        "aula": "Aula B [Edificio C9]",
        "orario": "12:00 - 14:00",
        "docente": "RAIMONDO DAVIDE MARTINO"
      },
      {
        "data": "06-11-2025",
        "aula": "Aula E Didattica [Edificio B]",
        "orario": "08:00 - 10:00",
        "docente": "SALVATO ERICA"
      },
      {
        "data": "07-11-2025",
        "aula": "Aula 3B [Edificio H2bis]",
        "orario": "13:00 - 15:00",
        "docente": "PELLEGRINO FELICE ANDREA"
      }
    ]
  }
]