[
  {
    "url": "https://orari.units.it/agendaweb/index.php?view=easycourse&form-type=corso&include=corso&txtcurr=&anno=2025&scuola=DipartimentodiFisica&corso=SM23A&anno2%5B%5D=SM23A%2B1%2B%7C1&visualizzazione_orario=cal&date=2025-11-17&periodo_didattico=&_lang=it&list=&week_grid_type=-1&ar_codes_=&ar_select_=&col_cells=0&empty_box=0&only_grid=0&highlighted_date=0&all_events=0&faculty_group=0",
    "dipartimento": "DipartimentodiFisica",
    "codice corso": "SM23A",
    "corso di studi": "FISICA (Laurea Magistrale)",
    "codice anno corso di studio": "SM23A+1+|1",
    "anno corso e curriculum": "1 - Fisica teorica",
    "giorno inizio settimana": "17/11/2025",
    "orario lezioni": [
      {
        "data": "17-11-2025",
        "aula": "Aula 4C [Edificio H2bis]",
        "orario": "09:00 - 11:00",
        "docente": "MECCHIA MATTIA"
      },
      {
        "data": "17-11-2025",
        "aula": "Aula 2C [Edificio H3]",
        "orario": "09:00 - 11:00",
        "docente": "Ansoldi Stefano"
      },
      {
        "data": "17-11-2025",
        "aula": "Aula E/Laboratorio T17 [Edificio F]",
        "orario": "11:00 - 13:00",
        "docente": "MILOTTI EDOARDO"
      },
      {
        "data": "17-11-2025",
        "aula": "Aula C [Edificio F]",
        "orario": "11:00 - 13:00",
        "docente": "COSLOVICH DANIELE"
      },
      {
        "data": "17-11-2025",
        "aula": "Aula A [Edificio F]",
        "orario": "13:00 - 15:00",
        "docente": "BASSI ANGELO"
      },
      {
        "data": "17-11-2025",
        "aula": "Aula 5A [Edificio H2bis]",
        "orario": "15:00 - 17:00",
        "docente": "BASSI ANGELO"
      },
      {
        "data": "17-11-2025",
        "aula": "Aula 4B [Edificio H2bis]",
        "orario": "17:00 - 19:00",
        "docente": "FARNETI RICCARDO, COPPOLA ERIKA, KUCHARSKI FRED"
      },
      {
        "data": "18-11-2025",
        "aula": "Aula B [Edificio C7]",
        "orario": "08:00 - 10:00",
        "docente": "MEDVET Eric"
      },
      {
        "data": "18-11-2025",
        "aula": "Aula E/Laboratorio T17 [Edificio F]",
        "orario": "09:00 - 11:00",
        "docente": "MILOTTI EDOARDO"
      },
      {
        "data": "18-11-2025",
        "aula": "Aula B [Edificio F]",
        "orario": "09:00 - 11:00",
        "docente": "IMPARATO ALBERTO"
      },
      {
        "data": "18-11-2025",
        "aula": "edificio F aula B",
        "orario": "09:00 - 11:00",
        "docente": "IMPARATO ALBERTO"
      },
      {
        "data": "18-11-2025",
        "aula": "Laboratorio T19 [Edificio F]",
        "orario": "11:00 - 13:00",
        "docente": "TROMBETTONI ANDREA, IMPARATO ALBERTO"
      },
      {
        "data": "18-11-2025",
        "aula": "Aula 3B [Edificio H2bis]",
        "orario": "11:00 - 13:00",
        "docente": "VALANDRO ROBERTO, DI PIETRO LORENZO"
      },
      {
        "data": "18-11-2025",
        "aula": "aula SISSA",
        "orario": "11:00 - 13:00",
        "docente": "GAVRYLENKO PAVLO"
      },
      {
        "data": "18-11-2025",
        "aula": "Aula C [Edificio C7]",
        "orario": "15:00 - 17:00",
        "docente": "BASSI ANGELO"
      },
      {
        "data": "18-11-2025",
        "aula": "Aula C [Edificio F]",
        "orario": "17:00 - 19:00",
        "docente": "BASSI ANGELO"
      },
      {
        "data": "19-11-2025",
        "aula": "Aula E/Laboratorio T17 [Edificio F]",
        "orario": "09:00 - 11:00",
        "docente": "MILOTTI EDOARDO"
      },
      {
        "data": "19-11-2025",
        "aula": "Aula 4C [Edificio H2bis]",
        "orario": "09:00 - 11:00",
        "docente": "TROMBETTONI ANDREA, IMPARATO ALBERTO"
      },
      {
        "data": "19-11-2025",
        "aula": "Aula B [Edificio F]",
        "orario": "11:00 - 13:00",
        "docente": "COSLOVICH DANIELE"
      },
      {
        "data": "19-11-2025",
        "aula": "Aula C [Edificio F]",
        "orario": "11:00 - 13:00",
        "docente": "BASSI ANGELO"
      },
      {
        "data": "19-11-2025",
        "aula": "Aula B [Edificio F]",
        "orario": "13:00 - 15:00",
        "docente": "IMPARATO ALBERTO"
      },
      {
        "data": "19-11-2025",
        "aula": "aula SISSA",
        "orario": "14:00 - 16:00",
        "docente": "GAVRYLENKO PAVLO"
      },
      {
        "data": "19-11-2025",
        "aula": "Aula B [Edificio F]",
        "orario": "15:00 - 17:00",
        "docente": "GABRIELLI Emidio"
      },
      {
        "data": "20-11-2025",
        "aula": "Aula B [Edificio F]",
        "orario": "09:00 - 11:00",
        "docente": ""
      },
      {
        "data": "20-11-2025",
        "aula": "Aula D [Edificio F]",
        "orario": "11:00 - 13:00",
        "docente": "MILOTTI EDOARDO"
      },
      {
        "data": "20-11-2025",
        "aula": "Aula B [Edificio F]",
        "orario": "12:00 - 14:00",
        "docente": "SCAZZA FRANCESCO"
      },
      {
        "data": "20-11-2025",
        "aula": "Aula 2C [Edificio H3]",
        "orario": "13:00 - 15:00",
        "docente": "MECCHIA MATTIA"
      },
      {
        "data": "20-11-2025",
        "aula": "Aula B [Edificio F]",
        "orario": "14:00 - 16:00",
        "docente": "VALANDRO ROBERTO, DI PIETRO LORENZO"
      },
      {
        "data": "20-11-2025",
        "aula": "Aula C [Edificio C7]",
        "orario": "16:00 - 19:00",
        "docente": "MEDVET Eric"
      },
      {
        "data": "21-11-2025",
        "aula": "Aula 4B [Edificio H2bis]",
        "orario": "09:00 - 11:00",
        "docente": "FARNETI RICCARDO, COPPOLA ERIKA, KUCHARSKI FRED"
      },
      {
        "data": "21-11-2025",
        "aula": "Aula C [Edificio F]",
        "orario": "13:00 - 14:00",
        "docente": "BASSI ANGELO"
      },
      {
        "data": "21-11-2025",
        "aula": "Aula E/Laboratorio T17 [Edificio F]",
        "orario": "13:00 - 14:00",
        "docente": "MILOTTI EDOARDO"
      },
      {
        "data": "21-11-2025",
        "aula": "Aula B [Edificio F]",
        "orario": "13:00 - 16:00",
        "docente": "SCAZZA FRANCESCO"
      },
      {
        "data": "21-11-2025",
        "aula": "Aula E/Laboratorio T17 [Edificio F]",
        "orario": "14:00 - 15:00",
        "docente": "MILOTTI EDOARDO"
      },
      {
        "data": "21-11-2025",
        "aula": "Aula 0B [Edificio H3]",
        "orario": "15:00 - 17:00",
        "docente": "GABRIELLI Emidio"
      }
    ]
  }
]